tomlkit_extras/__init__.py
tomlkit_extras/_constants.py
tomlkit_extras/_exceptions.py
tomlkit_extras/_file_validator.py
tomlkit_extras/_hierarchy.py
tomlkit_extras/_typing.py
tomlkit_extras/_utils.py
tomlkit_extras/descriptor/__init__.py
tomlkit_extras/descriptor/_descriptor.py
tomlkit_extras/descriptor/_descriptors.py
tomlkit_extras/descriptor/_helpers.py
tomlkit_extras/descriptor/_retriever.py
tomlkit_extras/descriptor/_store.py
tomlkit_extras/descriptor/_types.py
tomlkit_extras/py.typed
tomlkit_extras/toml/__init__.py
tomlkit_extras/toml/_comments.py
tomlkit_extras/toml/_delete.py
tomlkit_extras/toml/_insert.py
tomlkit_extras/toml/_out_of_order.py
tomlkit_extras/toml/_retrieval.py
tomlkit_extras/toml/_update.py
tomlkit_extras-0.1.0.dist-info/LICENSE
tomlkit_extras-0.1.0.dist-info/METADATA
tomlkit_extras-0.1.0.dist-info/WHEEL
tomlkit_extras-0.1.0.dist-info/RECORD
