Metadata-Version: 2.1
Name: tomlkit-extras
Version: 0.1.0
Summary: A Python package that extends the functionality of tomlkit, allowing for advanced manipulation, validation, and introspection of TOML files, including handling comments and nested structures
License: MIT
Author: galactixx
Requires-Python: >=3.10,<4.0
Classifier: License :: OSI Approved :: MIT License
Classifier: Programming Language :: Python :: 3
Classifier: Programming Language :: Python :: 3.10
Classifier: Programming Language :: Python :: 3.11
Classifier: Programming Language :: Python :: 3.12
Requires-Dist: charset-normalizer (>=3.3.2,<4.0.0)
Requires-Dist: pathvalidate (>=3.2.0,<4.0.0)
Requires-Dist: pyrsistent (>=0.20.0,<0.21.0)
Requires-Dist: tomlkit (>=0.13.0,<0.14.0)
